secsend_api/__init__.py
secsend_api/__version__.py
secsend_api/app.py
secsend_api/backend.py
secsend_api/backend_files.py
secsend_api/cors.py
secsend_api/metadata.py
secsend_api/options.py
secsend_api/prod.py
secsend_api/timeout.py
secsend_api-1.1.1.dist-info/METADATA
secsend_api-1.1.1.dist-info/WHEEL
secsend_api-1.1.1.dist-info/top_level.txt
secsend_api-1.1.1.dist-info/RECORD
